setup.py
python_resmon.egg-info/PKG-INFO
python_resmon.egg-info/SOURCES.txt
python_resmon.egg-info/dependency_links.txt
python_resmon.egg-info/entry_points.txt
python_resmon.egg-info/requires.txt
python_resmon.egg-info/top_level.txt
resmon/__init__.py
resmon/resmon.py