Metadata-Version: 1.1
Name: python-resmon
Version: 1.0.1
Summary: 
